{
  "Iklan":
  [
      {
      "status": "0",
      "link": "https://play.google.com/store/apps/details?id=com.kmb.betrandpetoonsu",
      "interid": "ca-app-pub-1385874687607024/3827088815",
      "nativeid": "ca-app-pub-1385874687607024/4146653015",
      "startappid": "209419592",
      "pengaturan_iklan": "1",
      "fan_inter": "1032076770619695_1032076800619692",
      "fan_banner_native": "1032076770619695_1032076797286359",
      "fan_native": "1032076770619695_1032076803953025",
      "hpk_admob1": "",
      "hpk_admob2": "",
      "hpk_admob3": "",
      "hpk_admob4": "",
      "hpk_admob5": ""
      }
   ]

}